bnc/__init__.py
bnc/builder.py
bnc/cli.py
bnc/config.json
bnc/decorators.py
bnc/environment.py
bnc/exceptions.py
bnc/logger.py
bnc/options.py
bnc/commands/__init__.py
bnc/commands/cmd_credentials.py
bnc/commands/cmd_market.py
bnc/commands/cmd_spot.py
bnc/utils/__init__.py
bnc/utils/api_time.py
bnc/utils/config.py
bnc/utils/security.py
bnc/utils/utils.py
bnc/validation/__init__.py
bnc/validation/val_cli.py
bnc/validation/val_market.py
bnc/validation/val_spot.py
bnc-0.0.3.dist-info/LICENSE
bnc-0.0.3.dist-info/METADATA
bnc-0.0.3.dist-info/WHEEL
bnc-0.0.3.dist-info/entry_points.txt
bnc-0.0.3.dist-info/top_level.txt
bnc-0.0.3.dist-info/RECORD
