Metadata-Version: 2.1
Name: bnc
Version: 0.0.3
Summary: Unofficial Binance CLI to interact with Binance API
Home-page: https://github.com/mpetrinidev/bnc-cli
Author: Mauro Petrini
Author-email: dev.mpetrini@gmail.com
License: UNKNOWN
Project-URL: Source, https://github.com/mpetrinidev/bnc-cli
Project-URL: Documentation, https://github.com/mpetrinidev/bnc-cli/wiki
Project-URL: Bug Reports, https://github.com/mpetrinidev/bnc-cli/issues
Keywords: bnc,binance,binance-api,binance-cli,bnc-cli
Platform: UNKNOWN
Classifier: Development Status :: 3 - Alpha
Classifier: Intended Audience :: Other Audience
Classifier: Topic :: Terminals
Classifier: Topic :: Utilities
Classifier: License :: OSI Approved :: MIT License
Classifier: Programming Language :: Python :: 3.8
Classifier: Programming Language :: Python :: 3.9
Requires-Python: >=3.8, <4
Requires-Dist: requests-async (~=0.6.2)
Requires-Dist: click (~=7.1.2)
Requires-Dist: pandas (~=1.2.2)
Requires-Dist: PyYAML (~=5.4.1)
Requires-Dist: jmespath (~=0.10.0)
Requires-Dist: colorama (~=0.4.4)
